juno_manager/__init__.py
juno_manager/app.py
juno_manager/banner.svg
juno_manager/cli.py
juno_manager-0.1.0.dist-info/LICENSE
juno_manager-0.1.0.dist-info/METADATA
juno_manager-0.1.0.dist-info/WHEEL
juno_manager-0.1.0.dist-info/entry_points.txt
juno_manager-0.1.0.dist-info/top_level.txt
juno_manager-0.1.0.dist-info/RECORD
