Metadata-Version: 2.2
Name: juno-manager
Version: 0.1.0
Summary: JupyterLab Virtual Environment Manager
Home-page: https://github.com/velocitatem/juno
Author: Daniel Rosel
Author-email: daniel@alves.world
Classifier: Development Status :: 3 - Alpha
Classifier: Intended Audience :: Developers
Classifier: Intended Audience :: Science/Research
Classifier: License :: OSI Approved :: MIT License
Classifier: Programming Language :: Python :: 3
Classifier: Programming Language :: Python :: 3.7
Classifier: Programming Language :: Python :: 3.8
Classifier: Programming Language :: Python :: 3.9
Classifier: Programming Language :: Python :: 3.10
Classifier: Topic :: Scientific/Engineering
Classifier: Topic :: Software Development :: User Interfaces
Requires-Python: >=3.7
License-File: LICENSE
Requires-Dist: PyQt5
Requires-Dist: jupyter
Requires-Dist: ipykernel
Dynamic: author
Dynamic: author-email
Dynamic: classifier
Dynamic: description
Dynamic: description-content-type
Dynamic: home-page
Dynamic: requires-dist
Dynamic: requires-python
Dynamic: summary
